chemonaut/__init__.py
chemonaut-0.1.0.dist-info/LICENSE.txt
chemonaut-0.1.0.dist-info/METADATA
chemonaut-0.1.0.dist-info/WHEEL
chemonaut-0.1.0.dist-info/RECORD
